{"v":4,"entries":{"atoms-button--docs":{"id":"atoms-button--docs","title":"atoms/Button","name":"Docs","importPath":"./src/components/atoms/Button/index.stories.tsx","type":"docs","tags":["docs","autodocs"],"storiesImports":[]},"atoms-button--default":{"type":"story","id":"atoms-button--default","name":"Default","title":"atoms/Button","importPath":"./src/components/atoms/Button/index.stories.tsx","tags":["story"]},"atoms-button--theme":{"type":"story","id":"atoms-button--theme","name":"Theme","title":"atoms/Button","importPath":"./src/components/atoms/Button/index.stories.tsx","tags":["story"]},"atoms-button--shape":{"type":"story","id":"atoms-button--shape","name":"Shape","title":"atoms/Button","importPath":"./src/components/atoms/Button/index.stories.tsx","tags":["story"]},"atoms-button--size":{"type":"story","id":"atoms-button--size","name":"Size","title":"atoms/Button","importPath":"./src/components/atoms/Button/index.stories.tsx","tags":["story"]},"atoms-button--icon":{"type":"story","id":"atoms-button--icon","name":"Icon","title":"atoms/Button","importPath":"./src/components/atoms/Button/index.stories.tsx","tags":["story"]},"atoms-button--delay":{"type":"story","id":"atoms-button--delay","name":"Delay","title":"atoms/Button","importPath":"./src/components/atoms/Button/index.stories.tsx","tags":["story"]},"atoms-focuslayer--docs":{"id":"atoms-focuslayer--docs","title":"atoms/FocusLayer","name":"Docs","importPath":"./src/components/atoms/FocusLayer/index.stories.tsx","type":"docs","tags":["docs","autodocs"],"storiesImports":[]},"atoms-focuslayer--default":{"type":"story","id":"atoms-focuslayer--default","name":"Default","title":"atoms/FocusLayer","importPath":"./src/components/atoms/FocusLayer/index.stories.tsx","tags":["story"]},"atoms-hr--docs":{"id":"atoms-hr--docs","title":"atoms/Hr","name":"Docs","importPath":"./src/components/atoms/Hr/index.stories.tsx","type":"docs","tags":["docs","autodocs"],"storiesImports":[]},"atoms-hr--default":{"type":"story","id":"atoms-hr--default","name":"Default","title":"atoms/Hr","importPath":"./src/components/atoms/Hr/index.stories.tsx","tags":["story"]},"atoms-input--docs":{"id":"atoms-input--docs","title":"atoms/Input","name":"Docs","importPath":"./src/components/atoms/Input/index.stories.tsx","type":"docs","tags":["docs","autodocs"],"storiesImports":[]},"atoms-input--default":{"type":"story","id":"atoms-input--default","name":"Default","title":"atoms/Input","importPath":"./src/components/atoms/Input/index.stories.tsx","tags":["story"]},"atoms-label--docs":{"id":"atoms-label--docs","title":"atoms/Label","name":"Docs","importPath":"./src/components/atoms/Label/index.stories.tsx","type":"docs","tags":["docs","autodocs"],"storiesImports":[]},"atoms-label--default":{"type":"story","id":"atoms-label--default","name":"Default","title":"atoms/Label","importPath":"./src/components/atoms/Label/index.stories.tsx","tags":["story"]},"atoms-link--docs":{"id":"atoms-link--docs","title":"atoms/Link","name":"Docs","importPath":"./src/components/atoms/Link/index.stories.tsx","type":"docs","tags":["docs","autodocs"],"storiesImports":[]},"atoms-link--default":{"type":"story","id":"atoms-link--default","name":"Default","title":"atoms/Link","importPath":"./src/components/atoms/Link/index.stories.tsx","tags":["story"]},"atoms-options--docs":{"id":"atoms-options--docs","title":"atoms/Options","name":"Docs","importPath":"./src/components/atoms/Options/index.stories.tsx","type":"docs","tags":["docs","autodocs"],"storiesImports":[]},"atoms-options--default":{"type":"story","id":"atoms-options--default","name":"Default","title":"atoms/Options","importPath":"./src/components/atoms/Options/index.stories.tsx","tags":["story"]},"atoms-options--multiple":{"type":"story","id":"atoms-options--multiple","name":"Multiple","title":"atoms/Options","importPath":"./src/components/atoms/Options/index.stories.tsx","tags":["story"]},"atoms-options--text-ellipsis":{"type":"story","id":"atoms-options--text-ellipsis","name":"Text Ellipsis","title":"atoms/Options","importPath":"./src/components/atoms/Options/index.stories.tsx","tags":["story"]},"atoms-skeleton--docs":{"id":"atoms-skeleton--docs","title":"atoms/Skeleton","name":"Docs","importPath":"./src/components/atoms/Skeleton/stories/index.stories.tsx","type":"docs","tags":["docs","autodocs"],"storiesImports":[]},"atoms-skeleton--default":{"type":"story","id":"atoms-skeleton--default","name":"Default","title":"atoms/Skeleton","importPath":"./src/components/atoms/Skeleton/stories/index.stories.tsx","tags":["story"]},"atoms-toast--docs":{"id":"atoms-toast--docs","title":"atoms/Toast","name":"Docs","importPath":"./src/components/atoms/Toast/index.stories.tsx","type":"docs","tags":["docs","autodocs"],"storiesImports":[]},"atoms-toast--default":{"type":"story","id":"atoms-toast--default","name":"Default","title":"atoms/Toast","importPath":"./src/components/atoms/Toast/index.stories.tsx","tags":["story"]},"atoms-toast--type":{"type":"story","id":"atoms-toast--type","name":"Type","title":"atoms/Toast","importPath":"./src/components/atoms/Toast/index.stories.tsx","tags":["story"]},"atoms-tooltip-area--docs":{"id":"atoms-tooltip-area--docs","title":"atoms/Tooltip/Area","name":"Docs","importPath":"./src/components/atoms/Tooltip/Area.stories.tsx","type":"docs","tags":["docs","autodocs"],"storiesImports":[]},"atoms-tooltip-area--default":{"type":"story","id":"atoms-tooltip-area--default","name":"Default","title":"atoms/Tooltip/Area","importPath":"./src/components/atoms/Tooltip/Area.stories.tsx","tags":["story"]},"atoms-tooltip-content--docs":{"id":"atoms-tooltip-content--docs","title":"atoms/Tooltip/Content","name":"Docs","importPath":"./src/components/atoms/Tooltip/Content.stories.tsx","type":"docs","tags":["docs","autodocs"],"storiesImports":[]},"atoms-tooltip-content--default":{"type":"story","id":"atoms-tooltip-content--default","name":"Default","title":"atoms/Tooltip/Content","importPath":"./src/components/atoms/Tooltip/Content.stories.tsx","tags":["story"]},"atoms-tooltip--docs":{"id":"atoms-tooltip--docs","title":"atoms/Tooltip","name":"Docs","importPath":"./src/components/atoms/Tooltip/index.stories.tsx","type":"docs","tags":["docs","autodocs"],"storiesImports":[]},"atoms-tooltip--default":{"type":"story","id":"atoms-tooltip--default","name":"Default","title":"atoms/Tooltip","importPath":"./src/components/atoms/Tooltip/index.stories.tsx","tags":["story"]},"molecules-accordion--docs":{"id":"molecules-accordion--docs","title":"molecules/Accordion","name":"Docs","importPath":"./src/components/molecules/Accordion/index.stories.tsx","type":"docs","tags":["docs","autodocs"],"storiesImports":[]},"molecules-accordion--default":{"type":"story","id":"molecules-accordion--default","name":"Default","title":"molecules/Accordion","importPath":"./src/components/molecules/Accordion/index.stories.tsx","tags":["story"]},"molecules-checktag--docs":{"id":"molecules-checktag--docs","title":"molecules/CheckTag","name":"Docs","importPath":"./src/components/molecules/CheckTag/index.stories.tsx","type":"docs","tags":["docs","autodocs"],"storiesImports":[]},"molecules-checktag--default":{"type":"story","id":"molecules-checktag--default","name":"Default","title":"molecules/CheckTag","importPath":"./src/components/molecules/CheckTag/index.stories.tsx","tags":["story"]},"molecules-checkbox--docs":{"id":"molecules-checkbox--docs","title":"molecules/Checkbox","name":"Docs","importPath":"./src/components/molecules/Checkbox/index.stories.tsx","type":"docs","tags":["docs","autodocs"],"storiesImports":[]},"molecules-checkbox--default":{"type":"story","id":"molecules-checkbox--default","name":"Default","title":"molecules/Checkbox","importPath":"./src/components/molecules/Checkbox/index.stories.tsx","tags":["story"]},"molecules-dropdown--docs":{"id":"molecules-dropdown--docs","title":"molecules/Dropdown","name":"Docs","importPath":"./src/components/molecules/Dropdown/index.stories.tsx","type":"docs","tags":["docs","autodocs"],"storiesImports":[]},"molecules-dropdown--default":{"type":"story","id":"molecules-dropdown--default","name":"Default","title":"molecules/Dropdown","importPath":"./src/components/molecules/Dropdown/index.stories.tsx","tags":["story"]},"molecules-file--docs":{"id":"molecules-file--docs","title":"molecules/File","name":"Docs","importPath":"./src/components/molecules/File/index.stories.tsx","type":"docs","tags":["docs","autodocs"],"storiesImports":[]},"molecules-file--default":{"type":"story","id":"molecules-file--default","name":"Default","title":"molecules/File","importPath":"./src/components/molecules/File/index.stories.tsx","tags":["story"]},"organisms-floatingmodal--docs":{"id":"organisms-floatingmodal--docs","title":"organisms/FloatingModal","name":"Docs","importPath":"./src/components/molecules/FloatingModal/index.stories.tsx","type":"docs","tags":["docs","autodocs"],"storiesImports":[]},"organisms-floatingmodal--default":{"type":"story","id":"organisms-floatingmodal--default","name":"Default","title":"organisms/FloatingModal","importPath":"./src/components/molecules/FloatingModal/index.stories.tsx","tags":["story"]},"molecules-infocard--docs":{"id":"molecules-infocard--docs","title":"molecules/InfoCard","name":"Docs","importPath":"./src/components/molecules/InfoCard/index.stories.tsx","type":"docs","tags":["docs","autodocs"],"storiesImports":[]},"molecules-infocard--default":{"type":"story","id":"molecules-infocard--default","name":"Default","title":"molecules/InfoCard","importPath":"./src/components/molecules/InfoCard/index.stories.tsx","tags":["story"]},"molecules-pagination--docs":{"id":"molecules-pagination--docs","title":"molecules/Pagination","name":"Docs","importPath":"./src/components/molecules/Pagination/index.stories.tsx","type":"docs","tags":["docs","autodocs"],"storiesImports":[]},"molecules-pagination--default":{"type":"story","id":"molecules-pagination--default","name":"Default","title":"molecules/Pagination","importPath":"./src/components/molecules/Pagination/index.stories.tsx","tags":["story"]},"molecules-searchbox--docs":{"id":"molecules-searchbox--docs","title":"molecules/Searchbox","name":"Docs","importPath":"./src/components/molecules/Searchbox/index.stories.tsx","type":"docs","tags":["docs","autodocs"],"storiesImports":[]},"molecules-searchbox--default":{"type":"story","id":"molecules-searchbox--default","name":"Default","title":"molecules/Searchbox","importPath":"./src/components/molecules/Searchbox/index.stories.tsx","tags":["story"]},"molecules-selectbox--docs":{"id":"molecules-selectbox--docs","title":"molecules/Selectbox","name":"Docs","importPath":"./src/components/molecules/Selectbox/index.stories.tsx","type":"docs","tags":["docs","autodocs"],"storiesImports":[]},"molecules-selectbox--default":{"type":"story","id":"molecules-selectbox--default","name":"Default","title":"molecules/Selectbox","importPath":"./src/components/molecules/Selectbox/index.stories.tsx","tags":["story"]},"molecules-selectbox--multiple":{"type":"story","id":"molecules-selectbox--multiple","name":"Multiple","title":"molecules/Selectbox","importPath":"./src/components/molecules/Selectbox/index.stories.tsx","tags":["story"]},"molecules-switch--docs":{"id":"molecules-switch--docs","title":"molecules/Switch","name":"Docs","importPath":"./src/components/molecules/Switch/index.stories.tsx","type":"docs","tags":["docs","autodocs"],"storiesImports":[]},"molecules-switch--default":{"type":"story","id":"molecules-switch--default","name":"Default","title":"molecules/Switch","importPath":"./src/components/molecules/Switch/index.stories.tsx","tags":["story"]},"molecules-tabmenu--docs":{"id":"molecules-tabmenu--docs","title":"molecules/TabMenu","name":"Docs","importPath":"./src/components/molecules/TabMenu/index.stories.tsx","type":"docs","tags":["docs","autodocs"],"storiesImports":[]},"molecules-tabmenu--default":{"type":"story","id":"molecules-tabmenu--default","name":"Default","title":"molecules/TabMenu","importPath":"./src/components/molecules/TabMenu/index.stories.tsx","tags":["story"]},"molecules-tabmenu--round":{"type":"story","id":"molecules-tabmenu--round","name":"Round","title":"molecules/TabMenu","importPath":"./src/components/molecules/TabMenu/index.stories.tsx","tags":["story"]},"molecules-table--docs":{"id":"molecules-table--docs","title":"molecules/Table","name":"Docs","importPath":"./src/components/molecules/Table/index.stories.tsx","type":"docs","tags":["docs","autodocs"],"storiesImports":[]},"molecules-table--default":{"type":"story","id":"molecules-table--default","name":"Default","title":"molecules/Table","importPath":"./src/components/molecules/Table/index.stories.tsx","tags":["story"]},"molecules-tag--docs":{"id":"molecules-tag--docs","title":"molecules/Tag","name":"Docs","importPath":"./src/components/molecules/Tag/index.stories.tsx","type":"docs","tags":["docs","autodocs"],"storiesImports":[]},"molecules-tag--default":{"type":"story","id":"molecules-tag--default","name":"Default","title":"molecules/Tag","importPath":"./src/components/molecules/Tag/index.stories.tsx","tags":["story"]},"molecules-tag--size":{"type":"story","id":"molecules-tag--size","name":"Size","title":"molecules/Tag","importPath":"./src/components/molecules/Tag/index.stories.tsx","tags":["story"]},"molecules-tag--color":{"type":"story","id":"molecules-tag--color","name":"Color","title":"molecules/Tag","importPath":"./src/components/molecules/Tag/index.stories.tsx","tags":["story"]},"molecules-tag--closable":{"type":"story","id":"molecules-tag--closable","name":"Closable","title":"molecules/Tag","importPath":"./src/components/molecules/Tag/index.stories.tsx","tags":["story"]},"molecules-textarea--docs":{"id":"molecules-textarea--docs","title":"molecules/Textarea","name":"Docs","importPath":"./src/components/molecules/Textarea/index.stories.tsx","type":"docs","tags":["docs","autodocs"],"storiesImports":[]},"molecules-textarea--default":{"type":"story","id":"molecules-textarea--default","name":"Default","title":"molecules/Textarea","importPath":"./src/components/molecules/Textarea/index.stories.tsx","tags":["story"]},"molecules-textbox--docs":{"id":"molecules-textbox--docs","title":"molecules/Textbox","name":"Docs","importPath":"./src/components/molecules/Textbox/index.stories.tsx","type":"docs","tags":["docs","autodocs"],"storiesImports":[]},"molecules-textbox--default":{"type":"story","id":"molecules-textbox--default","name":"Default","title":"molecules/Textbox","importPath":"./src/components/molecules/Textbox/index.stories.tsx","tags":["story"]},"molecules-toastcontainer--docs":{"id":"molecules-toastcontainer--docs","title":"molecules/ToastContainer","name":"Docs","importPath":"./src/components/molecules/ToastContainer/index.stories.tsx","type":"docs","tags":["docs","autodocs"],"storiesImports":[]},"molecules-toastcontainer--default":{"type":"story","id":"molecules-toastcontainer--default","name":"Default","title":"molecules/ToastContainer","importPath":"./src/components/molecules/ToastContainer/index.stories.tsx","tags":["story"]},"organisms-backofficepagination--docs":{"id":"organisms-backofficepagination--docs","title":"organisms/BackOfficePagination","name":"Docs","importPath":"./src/components/organisms/BackOfficePagination/index.stories.tsx","type":"docs","tags":["docs","autodocs"],"storiesImports":[]},"organisms-backofficepagination--default":{"type":"story","id":"organisms-backofficepagination--default","name":"Default","title":"organisms/BackOfficePagination","importPath":"./src/components/organisms/BackOfficePagination/index.stories.tsx","tags":["story"]},"organisms-confirmmodal--docs":{"id":"organisms-confirmmodal--docs","title":"organisms/ConfirmModal","name":"Docs","importPath":"./src/components/organisms/ConfirmModal/index.stories.tsx","type":"docs","tags":["docs","autodocs"],"storiesImports":[]},"organisms-confirmmodal--default":{"type":"story","id":"organisms-confirmmodal--default","name":"Default","title":"organisms/ConfirmModal","importPath":"./src/components/organisms/ConfirmModal/index.stories.tsx","tags":["story"]},"organisms-dateselectbox--docs":{"id":"organisms-dateselectbox--docs","title":"organisms/DateSelectbox","name":"Docs","importPath":"./src/components/organisms/DateSelectbox/index.stories.tsx","type":"docs","tags":["docs","autodocs"],"storiesImports":[]},"organisms-dateselectbox--default":{"type":"story","id":"organisms-dateselectbox--default","name":"Default","title":"organisms/DateSelectbox","importPath":"./src/components/organisms/DateSelectbox/index.stories.tsx","tags":["story"]},"organisms-drawermodal--docs":{"id":"organisms-drawermodal--docs","title":"organisms/DrawerModal","name":"Docs","importPath":"./src/components/organisms/DrawerModal/index.stories.tsx","type":"docs","tags":["docs","autodocs"],"storiesImports":[]},"organisms-drawermodal--default":{"type":"story","id":"organisms-drawermodal--default","name":"Default","title":"organisms/DrawerModal","importPath":"./src/components/organisms/DrawerModal/index.stories.tsx","tags":["story"]},"organisms-drawermodal--direction":{"type":"story","id":"organisms-drawermodal--direction","name":"Direction","title":"organisms/DrawerModal","importPath":"./src/components/organisms/DrawerModal/index.stories.tsx","tags":["story"]},"organisms-drawermodal--with-contents":{"type":"story","id":"organisms-drawermodal--with-contents","name":"With Contents","title":"organisms/DrawerModal","importPath":"./src/components/organisms/DrawerModal/index.stories.tsx","tags":["story"]},"organisms-dropdowntag--docs":{"id":"organisms-dropdowntag--docs","title":"organisms/DropdownTag","name":"Docs","importPath":"./src/components/organisms/DropdownTag/index.stories.tsx","type":"docs","tags":["docs","autodocs"],"storiesImports":[]},"organisms-dropdowntag--default":{"type":"story","id":"organisms-dropdowntag--default","name":"Default","title":"organisms/DropdownTag","importPath":"./src/components/organisms/DropdownTag/index.stories.tsx","tags":["story"]},"organisms-floatingactionmodal--docs":{"id":"organisms-floatingactionmodal--docs","title":"organisms/FloatingActionModal","name":"Docs","importPath":"./src/components/organisms/FloatingActionModal/index.stories.tsx","type":"docs","tags":["docs","autodocs"],"storiesImports":[]},"organisms-floatingactionmodal--default":{"type":"story","id":"organisms-floatingactionmodal--default","name":"Default","title":"organisms/FloatingActionModal","importPath":"./src/components/organisms/FloatingActionModal/index.stories.tsx","tags":["story"]},"organisms-modal--docs":{"id":"organisms-modal--docs","title":"organisms/Modal","name":"Docs","importPath":"./src/components/organisms/Modal/index.stories.tsx","type":"docs","tags":["docs","autodocs"],"storiesImports":[]},"organisms-modal--default":{"type":"story","id":"organisms-modal--default","name":"Default","title":"organisms/Modal","importPath":"./src/components/organisms/Modal/index.stories.tsx","tags":["story"]},"organisms-modal--with-tab-menu":{"type":"story","id":"organisms-modal--with-tab-menu","name":"With Tab Menu","title":"organisms/Modal","importPath":"./src/components/organisms/Modal/index.stories.tsx","tags":["story"]},"organisms-notfound--docs":{"id":"organisms-notfound--docs","title":"organisms/NotFound","name":"Docs","importPath":"./src/components/organisms/NotFound/index.stories.tsx","type":"docs","tags":["docs","autodocs"],"storiesImports":[]},"organisms-notfound--default":{"type":"story","id":"organisms-notfound--default","name":"Default","title":"organisms/NotFound","importPath":"./src/components/organisms/NotFound/index.stories.tsx","tags":["story"]},"organisms-optionsbutton--docs":{"id":"organisms-optionsbutton--docs","title":"organisms/OptionsButton","name":"Docs","importPath":"./src/components/organisms/OptionsButton/index.stories.tsx","type":"docs","tags":["docs","autodocs"],"storiesImports":[]},"organisms-optionsbutton--default":{"type":"story","id":"organisms-optionsbutton--default","name":"Default","title":"organisms/OptionsButton","importPath":"./src/components/organisms/OptionsButton/index.stories.tsx","tags":["story"]},"organisms-optionstag--docs":{"id":"organisms-optionstag--docs","title":"organisms/OptionsTag","name":"Docs","importPath":"./src/components/organisms/OptionsTag/index.stories.tsx","type":"docs","tags":["docs","autodocs"],"storiesImports":[]},"organisms-optionstag--default":{"type":"story","id":"organisms-optionstag--default","name":"Default","title":"organisms/OptionsTag","importPath":"./src/components/organisms/OptionsTag/index.stories.tsx","tags":["story"]},"organisms-partneraccordion--docs":{"id":"organisms-partneraccordion--docs","title":"organisms/PartnerAccordion","name":"Docs","importPath":"./src/components/organisms/PartnerAccordion/index.stories.tsx","type":"docs","tags":["docs","autodocs"],"storiesImports":[]},"organisms-partneraccordion--default":{"type":"story","id":"organisms-partneraccordion--default","name":"Default","title":"organisms/PartnerAccordion","importPath":"./src/components/organisms/PartnerAccordion/index.stories.tsx","tags":["story"]}}}
